eazyml_insight/__init__.py
eazyml_insight/Linux_x86_64/__init__.py
eazyml_insight/Linux_x86_64/eazyml_insight/__init__.cpython-310-x86_64-linux-gnu.so
eazyml_insight/Linux_x86_64/eazyml_insight/__init__.cpython-311-x86_64-linux-gnu.so
eazyml_insight/Linux_x86_64/eazyml_insight/__init__.cpython-312-x86_64-linux-gnu.so
eazyml_insight/Linux_x86_64/eazyml_insight/__init__.cpython-38-x86_64-linux-gnu.so
eazyml_insight/Linux_x86_64/eazyml_insight/__init__.cpython-39-x86_64-linux-gnu.so
eazyml_insight/Linux_x86_64/eazyml_insight/client.cpython-310-x86_64-linux-gnu.so
eazyml_insight/Linux_x86_64/eazyml_insight/client.cpython-311-x86_64-linux-gnu.so
eazyml_insight/Linux_x86_64/eazyml_insight/client.cpython-312-x86_64-linux-gnu.so
eazyml_insight/Linux_x86_64/eazyml_insight/client.cpython-38-x86_64-linux-gnu.so
eazyml_insight/Linux_x86_64/eazyml_insight/client.cpython-39-x86_64-linux-gnu.so
eazyml_insight/Linux_x86_64/eazyml_insight/test_client.cpython-310-x86_64-linux-gnu.so
eazyml_insight/Linux_x86_64/eazyml_insight/test_client.cpython-311-x86_64-linux-gnu.so
eazyml_insight/Linux_x86_64/eazyml_insight/test_client.cpython-312-x86_64-linux-gnu.so
eazyml_insight/Linux_x86_64/eazyml_insight/test_client.cpython-38-x86_64-linux-gnu.so
eazyml_insight/Linux_x86_64/eazyml_insight/test_client.cpython-39-x86_64-linux-gnu.so
eazyml_insight/Linux_x86_64/eazyml_insight/globals/__init__.cpython-310-x86_64-linux-gnu.so
eazyml_insight/Linux_x86_64/eazyml_insight/globals/__init__.cpython-311-x86_64-linux-gnu.so
eazyml_insight/Linux_x86_64/eazyml_insight/globals/__init__.cpython-312-x86_64-linux-gnu.so
eazyml_insight/Linux_x86_64/eazyml_insight/globals/__init__.cpython-38-x86_64-linux-gnu.so
eazyml_insight/Linux_x86_64/eazyml_insight/globals/__init__.cpython-39-x86_64-linux-gnu.so
eazyml_insight/Linux_x86_64/eazyml_insight/globals/config.cpython-310-x86_64-linux-gnu.so
eazyml_insight/Linux_x86_64/eazyml_insight/globals/config.cpython-311-x86_64-linux-gnu.so
eazyml_insight-0.0.60.dist-info/LICENSE
eazyml_insight-0.0.60.dist-info/METADATA
eazyml_insight-0.0.60.dist-info/WHEEL
eazyml_insight-0.0.60.dist-info/top_level.txt
eazyml_insight-0.0.60.dist-info/RECORD
